kona/__init__.py
kona/__main__.py
kona/core/__init__.py
kona/core/sync.py
kona/external/__init__.py
kona/external/abc.py
kona/external/ctfd.py
kona/external/rctf.py
kona/schema/__init__.py
kona/schema/models.py
kona/schema/parsers.py
kona/util/__init__.py
kona/util/jinja.py
kona/util/tar.py
konata-0.0.1.dist-info/METADATA
konata-0.0.1.dist-info/WHEEL
konata-0.0.1.dist-info/licenses/LICENSE
konata-0.0.1.dist-info/RECORD
