Metadata-Version: 2.4
Name: konata
Version: 0.0.1
Summary: a CTF tool for managing challenges and deploying them across multiple CTF platforms
Project-URL: source, https://github.com/project-sekai-ctf/konata
Author-email: es3n1n <git@es3n1n.im>
License-Expression: Apache-2.0
License-File: LICENSE
Requires-Python: >=3.13
Requires-Dist: click>=8.3.0
Requires-Dist: httpx>=0.28.1
Requires-Dist: jinja2>=3.1.6
Requires-Dist: loguru>=0.7.3
Requires-Dist: pydantic>=2.11.9
Requires-Dist: pyyaml>=6.0.2
Requires-Dist: uvloop>=0.21.0; sys_platform != 'win32'
